fpipe/__init__.py
fpipe/exceptions.py
fpipe/workflow.py
fpipe/file/__init__.py
fpipe/file/byte.py
fpipe/file/file.py
fpipe/file/ftp.py
fpipe/file/local.py
fpipe/file/s3.py
fpipe/gen/__init__.py
fpipe/gen/flush.py
fpipe/gen/ftp.py
fpipe/gen/generator.py
fpipe/gen/local.py
fpipe/gen/meta.py
fpipe/gen/program.py
fpipe/gen/s3.py
fpipe/gen/tar.py
fpipe/meta/__init__.py
fpipe/meta/abstract.py
fpipe/meta/blocksize.py
fpipe/meta/bucket.py
fpipe/meta/checksum.py
fpipe/meta/host.py
fpipe/meta/mime.py
fpipe/meta/modified.py
fpipe/meta/password.py
fpipe/meta/path.py
fpipe/meta/port.py
fpipe/meta/prefix.py
fpipe/meta/s3.py
fpipe/meta/size.py
fpipe/meta/stream.py
fpipe/meta/username.py
fpipe/meta/version.py
fpipe/utils/__init__.py
fpipe/utils/bytesloop.py
fpipe/utils/const.py
fpipe/utils/ftp.py
fpipe/utils/meta.py
fpipe/utils/mime.py
fpipe/utils/multipart_buffer.py
fpipe/utils/s3_reader.py
fpipe/utils/s3_writer.py
fpipe/utils/s3_writer_worker.py
fpipe-0.0.24.dist-info/AUTHORS.rst
fpipe-0.0.24.dist-info/LICENSE.txt
fpipe-0.0.24.dist-info/METADATA
fpipe-0.0.24.dist-info/WHEEL
fpipe-0.0.24.dist-info/top_level.txt
fpipe-0.0.24.dist-info/RECORD
