Metadata-Version: 2.1
Name: fpipe
Version: 0.0.24
Summary: Library for working with file-likes as piped streams
Home-page: https://github.com/vkvam/fpipe
Author: Vemund Kvam
Author-email: vemund.kvam@gmail.com
License: MIT
Keywords: pipe file stream
Platform: UNKNOWN
Classifier: Development Status :: 3 - Alpha
Classifier: License :: OSI Approved :: MIT License
Classifier: Programming Language :: Python
Classifier: Programming Language :: Python :: 3.6
Classifier: Programming Language :: Python :: 3.7
Classifier: Programming Language :: Python :: 3.8
Classifier: Intended Audience :: Developers
Requires-Dist: botocore (>=1.13.40)
